netwk/__init__.py
netwk/activations.py
netwk-2.12.5.dist-info/LICENSE
netwk-2.12.5.dist-info/METADATA
netwk-2.12.5.dist-info/WHEEL
netwk-2.12.5.dist-info/top_level.txt
netwk-2.12.5.dist-info/RECORD
