Metadata-Version: 2.1
Name: netwk
Version: 2.12.5
Summary: Create fast, optimized, and easy-to-use neural networks.
Home-page: https://github.com/flowa-ai/netwk
Author: flowa.ai
Author-email: flowa.dev@gmail.com
Keywords: network,machine learning,ai,neural network
Classifier: Development Status :: 5 - Production/Stable
Classifier: Intended Audience :: Developers
Classifier: License :: OSI Approved :: MIT License
Classifier: Programming Language :: Python :: 3
Classifier: Topic :: Software Development :: Libraries :: Python Modules
Classifier: Topic :: Scientific/Engineering :: Artificial Intelligence
Classifier: Topic :: Scientific/Engineering :: Mathematics
Requires-Python: >=3.6
License-File: LICENSE
Requires-Dist: numpy
